universal_mcp_unipile/README.md
universal_mcp_unipile/__init__.py
universal_mcp_unipile/app.py
universal_mcp_unipile/server.py
universal_mcp_unipile-0.1.13.dist-info/METADATA
universal_mcp_unipile-0.1.13.dist-info/WHEEL
universal_mcp_unipile-0.1.13.dist-info/entry_points.txt
universal_mcp_unipile-0.1.13.dist-info/licenses/LICENSE
universal_mcp_unipile-0.1.13.dist-info/RECORD
